epicscorelibs/Com.pxd
epicscorelibs/Comxx.pxd
epicscorelibs/__init__.pxd
epicscorelibs/__init__.py
epicscorelibs/_base.cpython-311-darwin.so
epicscorelibs/_config.py
epicscorelibs/ca.pxd
epicscorelibs/config.py
epicscorelibs/dbCore.pxd
epicscorelibs/ioc.py
epicscorelibs/version.py
epicscorelibs/ca/__init__.py
epicscorelibs/ca/cadef.py
epicscorelibs/ca/dbr.py
epicscorelibs/ca/py23.py
epicscorelibs/dbd/PVAClientRegister.dbd
epicscorelibs/dbd/PVACommonRegister.dbd
epicscorelibs/dbd/PVAServerRegister.dbd
epicscorelibs/dbd/aSubRecord.dbd
epicscorelibs/dbd/aaiRecord.dbd
epicscorelibs/dbd/aaoRecord.dbd
epicscorelibs/dbd/aiRecord.dbd
epicscorelibs/dbd/aoRecord.dbd
epicscorelibs/dbd/asSub.dbd
epicscorelibs/dbd/base.dbd
epicscorelibs/dbd/biRecord.dbd
epicscorelibs/dbd/boRecord.dbd
epicscorelibs/dbd/bptTypeJdegC.dbd
epicscorelibs/dbd/bptTypeJdegF.dbd
epicscorelibs/dbd/bptTypeKdegC.dbd
epicscorelibs/dbd/bptTypeKdegF.dbd
epicscorelibs/dbd/calcRecord.dbd
epicscorelibs/dbd/calcoutRecord.dbd
epicscorelibs/dbd/compressRecord.dbd
epicscorelibs/dbd/dbCommon.dbd
epicscorelibs/dbd/dbCommonRecord.dbd
epicscorelibs/dbd/dbCore.dbd
epicscorelibs/dbd/devSoft.dbd
epicscorelibs/dbd/dfanoutRecord.dbd
epicscorelibs/dbd/dlload.dbd
epicscorelibs/dbd/eventRecord.dbd
epicscorelibs/dbd/fanoutRecord.dbd
epicscorelibs/dbd/filters.dbd
epicscorelibs/dbd/histogramRecord.dbd
epicscorelibs/dbd/int64inRecord.dbd
epicscorelibs/dbd/int64outRecord.dbd
epicscorelibs/dbd/links.dbd
epicscorelibs/dbd/longinRecord.dbd
epicscorelibs/dbd/longoutRecord.dbd
epicscorelibs/dbd/lsiRecord.dbd
epicscorelibs/dbd/lsoRecord.dbd
epicscorelibs/dbd/mbbiDirectRecord.dbd
epicscorelibs/dbd/mbbiRecord.dbd
epicscorelibs/dbd/mbboDirectRecord.dbd
epicscorelibs/dbd/mbboRecord.dbd
epicscorelibs/dbd/menuAlarmSevr.dbd
epicscorelibs/dbd/menuAlarmStat.dbd
epicscorelibs/dbd/menuConvert.dbd
epicscorelibs/dbd/menuFtype.dbd
epicscorelibs/dbd/menuGlobal.dbd
epicscorelibs/dbd/menuIvoa.dbd
epicscorelibs/dbd/menuOmsl.dbd
epicscorelibs-7.0.10.99.0.0.dist-info/licenses/LICENSE
epicscorelibs-7.0.10.99.0.0.dist-info/METADATA
epicscorelibs-7.0.10.99.0.0.dist-info/WHEEL
epicscorelibs-7.0.10.99.0.0.dist-info/top_level.txt
epicscorelibs-7.0.10.99.0.0.dist-info/RECORD
